broadcaster/__init__.py
broadcaster/_base.py
broadcaster/py.typed
broadcaster/backends/__init__.py
broadcaster/backends/base.py
broadcaster/backends/kafka.py
broadcaster/backends/memory.py
broadcaster/backends/postgres.py
broadcaster/backends/redis.py
panthera_broadcaster-0.4.0.dist-info/METADATA
panthera_broadcaster-0.4.0.dist-info/WHEEL
panthera_broadcaster-0.4.0.dist-info/licenses/LICENSE.md
panthera_broadcaster-0.4.0.dist-info/RECORD
