Metadata-Version: 2.4
Name: panthera-broadcaster
Version: 0.4.0
Summary: Simple broadcast channels.
Project-URL: Homepage, https://github.com/encode/broadcaster
Author: DanTolken
License-Expression: BSD-3-Clause
License-File: LICENSE.md
Classifier: Development Status :: 3 - Alpha
Classifier: Environment :: Web Environment
Classifier: Intended Audience :: Developers
Classifier: License :: OSI Approved :: BSD License
Classifier: Operating System :: OS Independent
Classifier: Programming Language :: Python :: 3
Classifier: Programming Language :: Python :: 3.8
Classifier: Programming Language :: Python :: 3.9
Classifier: Programming Language :: Python :: 3.10
Classifier: Programming Language :: Python :: 3.11
Classifier: Programming Language :: Python :: 3.12
Classifier: Topic :: Internet :: WWW/HTTP
Requires-Python: >=3.8
Requires-Dist: anyio<5,>=3.4.0
Requires-Dist: typing-extensions>=3.10.0; python_version < '3.10'
Provides-Extra: kafka
Requires-Dist: aiokafka; extra == 'kafka'
Provides-Extra: postgres
Requires-Dist: asyncpg; extra == 'postgres'
Provides-Extra: redis
Requires-Dist: redis; extra == 'redis'
Provides-Extra: test
Requires-Dist: pytest; extra == 'test'
Requires-Dist: pytest-asyncio; extra == 'test'
